scikit_package/__init__.py
scikit_package/scikit_package_app.py
scikit_package/version.py
scikit_package/cli/add.py
scikit_package/cli/create.py
scikit_package/cli/build/api_doc.py
scikit_package/cli/update/cf.py
scikit_package/utils/auth.py
scikit_package/utils/cookie.py
scikit_package/utils/io.py
scikit_package/utils/pypi.py
scikit_package/utils/shell.py
scikit_package-0.2.1.dist-info/licenses/AUTHORS.rst
scikit_package-0.2.1.dist-info/licenses/LICENSE.rst
scikit_package-0.2.1.dist-info/METADATA
scikit_package-0.2.1.dist-info/WHEEL
scikit_package-0.2.1.dist-info/entry_points.txt
scikit_package-0.2.1.dist-info/top_level.txt
scikit_package-0.2.1.dist-info/RECORD
