Metadata-Version: 2.4
Name: scikit-package
Version: 0.2.1
Summary: A Python package standard and generator for scientific code. Use scikit-package to launch a new project or migrate existing ones to support the latest Python versions and streamline the process of distributing and maintaining your software package.
Author-email: "Simon J.L. Billinge" <sb2896@columbia.edu>, Sangjoon Lee <bobleesj@gmail.com>, Andrew Yang <ay2546@columbia.edu>, Caden Myers <cjm2304@columbia.edu>, Tieqiong Zhang <tz2600@columbia.edu>
Maintainer-email: "Simon J.L. Billinge" <sb2896@columbia.edu>, Sangjoon Lee <bobleesj@gmail.com>
Project-URL: Homepage, https://github.com/scikit-package/scikit-package/
Project-URL: Issues, https://github.com/scikit-package/scikit-package/issues/
Keywords: Package template,open-source software
Classifier: Development Status :: 3 - Alpha
Classifier: Environment :: Console
Classifier: Intended Audience :: Developers
Classifier: Intended Audience :: Science/Research
Classifier: License :: OSI Approved :: BSD License
Classifier: Operating System :: MacOS :: MacOS X
Classifier: Operating System :: Microsoft :: Windows
Classifier: Operating System :: POSIX
Classifier: Operating System :: Unix
Classifier: Programming Language :: Python :: 3.11
Classifier: Programming Language :: Python :: 3.12
Classifier: Programming Language :: Python :: 3.13
Classifier: Topic :: Scientific/Engineering :: Physics
Classifier: Topic :: Scientific/Engineering :: Chemistry
Requires-Python: <3.14,>=3.11
License-File: LICENSE.rst
License-File: AUTHORS.rst
Requires-Dist: cookiecutter
Requires-Dist: click
Requires-Dist: packaging
Dynamic: license-file
